mlslib/__init__.py
mlslib/bigquery_utils.py
mlslib/date_utils.py
mlslib/display_utils.py
mlslib/evaluate_utils.py
mlslib/gcs_utils.py
mlslib/sampling_utils.py
mlslib-0.1.12.dist-info/METADATA
mlslib-0.1.12.dist-info/WHEEL
mlslib-0.1.12.dist-info/top_level.txt
mlslib-0.1.12.dist-info/RECORD
